<annotation>
	<folder>JPEGImages</folder>
	<filename>微信图片_2020010614210113.jpg</filename>
	<path>C:\Users\HaYukima\Desktop\JPEGImages\微信图片_2020010614210113.jpg</path>
	<source>
		<database>Unknown</database>
	</source>
	<size>
		<width>4032</width>
		<height>3024</height>
		<depth>3</depth>
	</size>
	<segmented>0</segmented>
	<object>
		<name>5</name>
		<pose>Unspecified</pose>
		<truncated>0</truncated>
		<difficult>0</difficult>
		<bndbox>
			<xmin>853</xmin>
			<ymin>497</ymin>
			<xmax>1033</xmax>
			<ymax>692</ymax>
		</bndbox>
	</object>
	<object>
		<name>5</name>
		<pose>Unspecified</pose>
		<truncated>0</truncated>
		<difficult>0</difficult>
		<bndbox>
			<xmin>1983</xmin>
			<ymin>2342</ymin>
			<xmax>2188</xmax>
			<ymax>2582</ymax>
		</bndbox>
	</object>
	<object>
		<name>5</name>
		<pose>Unspecified</pose>
		<truncated>0</truncated>
		<difficult>0</difficult>
		<bndbox>
			<xmin>2218</xmin>
			<ymin>2637</ymin>
			<xmax>2443</xmax>
			<ymax>2882</ymax>
		</bndbox>
	</object>
	<object>
		<name>5</name>
		<pose>Unspecified</pose>
		<truncated>0</truncated>
		<difficult>0</difficult>
		<bndbox>
			<xmin>3233</xmin>
			<ymin>1222</ymin>
			<xmax>3483</xmax>
			<ymax>1457</ymax>
		</bndbox>
	</object>
	<object>
		<name>3</name>
		<pose>Unspecified</pose>
		<truncated>0</truncated>
		<difficult>0</difficult>
		<bndbox>
			<xmin>2648</xmin>
			<ymin>797</ymin>
			<xmax>2923</xmax>
			<ymax>1072</ymax>
		</bndbox>
	</object>
	<object>
		<name>3</name>
		<pose>Unspecified</pose>
		<truncated>0</truncated>
		<difficult>0</difficult>
		<bndbox>
			<xmin>2538</xmin>
			<ymin>1552</ymin>
			<xmax>2758</xmax>
			<ymax>1787</ymax>
		</bndbox>
	</object>
	<object>
		<name>3</name>
		<pose>Unspecified</pose>
		<truncated>0</truncated>
		<difficult>0</difficult>
		<bndbox>
			<xmin>1973</xmin>
			<ymin>1687</ymin>
			<xmax>2163</xmax>
			<ymax>1902</ymax>
		</bndbox>
	</object>
	<object>
		<name>3</name>
		<pose>Unspecified</pose>
		<truncated>0</truncated>
		<difficult>0</difficult>
		<bndbox>
			<xmin>2033</xmin>
			<ymin>1872</ymin>
			<xmax>2263</xmax>
			<ymax>2102</ymax>
		</bndbox>
	</object>
	<object>
		<name>3</name>
		<pose>Unspecified</pose>
		<truncated>0</truncated>
		<difficult>0</difficult>
		<bndbox>
			<xmin>1733</xmin>
			<ymin>1702</ymin>
			<xmax>1968</xmax>
			<ymax>1902</ymax>
		</bndbox>
	</object>
	<object>
		<name>3</name>
		<pose>Unspecified</pose>
		<truncated>0</truncated>
		<difficult>0</difficult>
		<bndbox>
			<xmin>803</xmin>
			<ymin>1647</ymin>
			<xmax>1118</xmax>
			<ymax>1897</ymax>
		</bndbox>
	</object>
	<object>
		<name>3</name>
		<pose>Unspecified</pose>
		<truncated>0</truncated>
		<difficult>0</difficult>
		<bndbox>
			<xmin>918</xmin>
			<ymin>1807</ymin>
			<xmax>1163</xmax>
			<ymax>2067</ymax>
		</bndbox>
	</object>
	<object>
		<name>3</name>
		<pose>Unspecified</pose>
		<truncated>0</truncated>
		<difficult>0</difficult>
		<bndbox>
			<xmin>853</xmin>
			<ymin>792</ymin>
			<xmax>1133</xmax>
			<ymax>1022</ymax>
		</bndbox>
	</object>
	<object>
		<name>3</name>
		<pose>Unspecified</pose>
		<truncated>0</truncated>
		<difficult>0</difficult>
		<bndbox>
			<xmin>888</xmin>
			<ymin>962</ymin>
			<xmax>1268</xmax>
			<ymax>1237</ymax>
		</bndbox>
	</object>
	<object>
		<name>4</name>
		<pose>Unspecified</pose>
		<truncated>0</truncated>
		<difficult>0</difficult>
		<bndbox>
			<xmin>1048</xmin>
			<ymin>417</ymin>
			<xmax>1253</xmax>
			<ymax>662</ymax>
		</bndbox>
	</object>
	<object>
		<name>4</name>
		<pose>Unspecified</pose>
		<truncated>0</truncated>
		<difficult>0</difficult>
		<bndbox>
			<xmin>2788</xmin>
			<ymin>1782</ymin>
			<xmax>3043</xmax>
			<ymax>2042</ymax>
		</bndbox>
	</object>
	<object>
		<name>4</name>
		<pose>Unspecified</pose>
		<truncated>0</truncated>
		<difficult>0</difficult>
		<bndbox>
			<xmin>1873</xmin>
			<ymin>1857</ymin>
			<xmax>2058</xmax>
			<ymax>2082</ymax>
		</bndbox>
	</object>
	<object>
		<name>6</name>
		<pose>Unspecified</pose>
		<truncated>0</truncated>
		<difficult>0</difficult>
		<bndbox>
			<xmin>1698</xmin>
			<ymin>1867</ymin>
			<xmax>1863</xmax>
			<ymax>2067</ymax>
		</bndbox>
	</object>
	<object>
		<name>3</name>
		<pose>Unspecified</pose>
		<truncated>0</truncated>
		<difficult>0</difficult>
		<bndbox>
			<xmin>1693</xmin>
			<ymin>2182</ymin>
			<xmax>1933</xmax>
			<ymax>2482</ymax>
		</bndbox>
	</object>
</annotation>
