<annotation>
	<folder>JPEGImages</folder>
	<filename>微信图片_202007150958174.jpg</filename>
	<path>C:\Users\HaYukima\Desktop\JPEGImages\微信图片_202007150958174.jpg</path>
	<source>
		<database>Unknown</database>
	</source>
	<size>
		<width>4032</width>
		<height>3024</height>
		<depth>3</depth>
	</size>
	<segmented>0</segmented>
	<object>
		<name>5</name>
		<pose>Unspecified</pose>
		<truncated>0</truncated>
		<difficult>0</difficult>
		<bndbox>
			<xmin>2383</xmin>
			<ymin>17</ymin>
			<xmax>2643</xmax>
			<ymax>237</ymax>
		</bndbox>
	</object>
	<object>
		<name>5</name>
		<pose>Unspecified</pose>
		<truncated>0</truncated>
		<difficult>0</difficult>
		<bndbox>
			<xmin>1383</xmin>
			<ymin>687</ymin>
			<xmax>1663</xmax>
			<ymax>972</ymax>
		</bndbox>
	</object>
	<object>
		<name>5</name>
		<pose>Unspecified</pose>
		<truncated>0</truncated>
		<difficult>0</difficult>
		<bndbox>
			<xmin>2568</xmin>
			<ymin>732</ymin>
			<xmax>2813</xmax>
			<ymax>982</ymax>
		</bndbox>
	</object>
	<object>
		<name>5</name>
		<pose>Unspecified</pose>
		<truncated>0</truncated>
		<difficult>0</difficult>
		<bndbox>
			<xmin>1958</xmin>
			<ymin>1627</ymin>
			<xmax>2198</xmax>
			<ymax>1847</ymax>
		</bndbox>
	</object>
	<object>
		<name>5</name>
		<pose>Unspecified</pose>
		<truncated>0</truncated>
		<difficult>0</difficult>
		<bndbox>
			<xmin>2058</xmin>
			<ymin>1817</ymin>
			<xmax>2263</xmax>
			<ymax>2012</ymax>
		</bndbox>
	</object>
	<object>
		<name>5</name>
		<pose>Unspecified</pose>
		<truncated>0</truncated>
		<difficult>0</difficult>
		<bndbox>
			<xmin>1538</xmin>
			<ymin>2272</ymin>
			<xmax>1773</xmax>
			<ymax>2537</ymax>
		</bndbox>
	</object>
	<object>
		<name>5</name>
		<pose>Unspecified</pose>
		<truncated>0</truncated>
		<difficult>0</difficult>
		<bndbox>
			<xmin>1178</xmin>
			<ymin>1247</ymin>
			<xmax>1413</xmax>
			<ymax>1487</ymax>
		</bndbox>
	</object>
	<object>
		<name>4</name>
		<pose>Unspecified</pose>
		<truncated>0</truncated>
		<difficult>0</difficult>
		<bndbox>
			<xmin>2298</xmin>
			<ymin>237</ymin>
			<xmax>2528</xmax>
			<ymax>412</ymax>
		</bndbox>
	</object>
</annotation>
