<annotation>
	<folder>JPEGImages</folder>
	<filename>微信图片_2020071614173717.jpg</filename>
	<path>C:\Users\HaYukima\Desktop\JPEGImages\微信图片_2020071614173717.jpg</path>
	<source>
		<database>Unknown</database>
	</source>
	<size>
		<width>4032</width>
		<height>3024</height>
		<depth>3</depth>
	</size>
	<segmented>0</segmented>
	<object>
		<name>x</name>
		<pose>Unspecified</pose>
		<truncated>0</truncated>
		<difficult>0</difficult>
		<bndbox>
			<xmin>1503</xmin>
			<ymin>1702</ymin>
			<xmax>1728</xmax>
			<ymax>1927</ymax>
		</bndbox>
	</object>
	<object>
		<name>x</name>
		<pose>Unspecified</pose>
		<truncated>0</truncated>
		<difficult>0</difficult>
		<bndbox>
			<xmin>1713</xmin>
			<ymin>2517</ymin>
			<xmax>1908</xmax>
			<ymax>2697</ymax>
		</bndbox>
	</object>
	<object>
		<name>x</name>
		<pose>Unspecified</pose>
		<truncated>0</truncated>
		<difficult>0</difficult>
		<bndbox>
			<xmin>2248</xmin>
			<ymin>2297</ymin>
			<xmax>2413</xmax>
			<ymax>2472</ymax>
		</bndbox>
	</object>
	<object>
		<name>x</name>
		<pose>Unspecified</pose>
		<truncated>0</truncated>
		<difficult>0</difficult>
		<bndbox>
			<xmin>2623</xmin>
			<ymin>2497</ymin>
			<xmax>2843</xmax>
			<ymax>2747</ymax>
		</bndbox>
	</object>
	<object>
		<name>x</name>
		<pose>Unspecified</pose>
		<truncated>1</truncated>
		<difficult>0</difficult>
		<bndbox>
			<xmin>1493</xmin>
			<ymin>2857</ymin>
			<xmax>1643</xmax>
			<ymax>3024</ymax>
		</bndbox>
	</object>
	<object>
		<name>x</name>
		<pose>Unspecified</pose>
		<truncated>0</truncated>
		<difficult>0</difficult>
		<bndbox>
			<xmin>613</xmin>
			<ymin>2002</ymin>
			<xmax>813</xmax>
			<ymax>2217</ymax>
		</bndbox>
	</object>
	<object>
		<name>5</name>
		<pose>Unspecified</pose>
		<truncated>0</truncated>
		<difficult>0</difficult>
		<bndbox>
			<xmin>913</xmin>
			<ymin>507</ymin>
			<xmax>1088</xmax>
			<ymax>717</ymax>
		</bndbox>
	</object>
	<object>
		<name>5</name>
		<pose>Unspecified</pose>
		<truncated>0</truncated>
		<difficult>0</difficult>
		<bndbox>
			<xmin>1228</xmin>
			<ymin>557</ymin>
			<xmax>1443</xmax>
			<ymax>762</ymax>
		</bndbox>
	</object>
	<object>
		<name>5</name>
		<pose>Unspecified</pose>
		<truncated>0</truncated>
		<difficult>0</difficult>
		<bndbox>
			<xmin>1423</xmin>
			<ymin>352</ymin>
			<xmax>1648</xmax>
			<ymax>497</ymax>
		</bndbox>
	</object>
	<object>
		<name>5</name>
		<pose>Unspecified</pose>
		<truncated>0</truncated>
		<difficult>0</difficult>
		<bndbox>
			<xmin>1373</xmin>
			<ymin>752</ymin>
			<xmax>1558</xmax>
			<ymax>942</ymax>
		</bndbox>
	</object>
	<object>
		<name>5</name>
		<pose>Unspecified</pose>
		<truncated>0</truncated>
		<difficult>0</difficult>
		<bndbox>
			<xmin>1523</xmin>
			<ymin>972</ymin>
			<xmax>1778</xmax>
			<ymax>1172</ymax>
		</bndbox>
	</object>
	<object>
		<name>5</name>
		<pose>Unspecified</pose>
		<truncated>0</truncated>
		<difficult>0</difficult>
		<bndbox>
			<xmin>1528</xmin>
			<ymin>1422</ymin>
			<xmax>1703</xmax>
			<ymax>1607</ymax>
		</bndbox>
	</object>
	<object>
		<name>5</name>
		<pose>Unspecified</pose>
		<truncated>0</truncated>
		<difficult>0</difficult>
		<bndbox>
			<xmin>1658</xmin>
			<ymin>1387</ymin>
			<xmax>1853</xmax>
			<ymax>1592</ymax>
		</bndbox>
	</object>
	<object>
		<name>5</name>
		<pose>Unspecified</pose>
		<truncated>0</truncated>
		<difficult>0</difficult>
		<bndbox>
			<xmin>2713</xmin>
			<ymin>1732</ymin>
			<xmax>2923</xmax>
			<ymax>1957</ymax>
		</bndbox>
	</object>
	<object>
		<name>5</name>
		<pose>Unspecified</pose>
		<truncated>0</truncated>
		<difficult>0</difficult>
		<bndbox>
			<xmin>1253</xmin>
			<ymin>1737</ymin>
			<xmax>1478</xmax>
			<ymax>1932</ymax>
		</bndbox>
	</object>
	<object>
		<name>3</name>
		<pose>Unspecified</pose>
		<truncated>0</truncated>
		<difficult>0</difficult>
		<bndbox>
			<xmin>1833</xmin>
			<ymin>1377</ymin>
			<xmax>2058</xmax>
			<ymax>1632</ymax>
		</bndbox>
	</object>
	<object>
		<name>4</name>
		<pose>Unspecified</pose>
		<truncated>0</truncated>
		<difficult>0</difficult>
		<bndbox>
			<xmin>2148</xmin>
			<ymin>1147</ymin>
			<xmax>2358</xmax>
			<ymax>1367</ymax>
		</bndbox>
	</object>
	<object>
		<name>4</name>
		<pose>Unspecified</pose>
		<truncated>0</truncated>
		<difficult>0</difficult>
		<bndbox>
			<xmin>2303</xmin>
			<ymin>1282</ymin>
			<xmax>2463</xmax>
			<ymax>1482</ymax>
		</bndbox>
	</object>
	<object>
		<name>5</name>
		<pose>Unspecified</pose>
		<truncated>0</truncated>
		<difficult>0</difficult>
		<bndbox>
			<xmin>1733</xmin>
			<ymin>2807</ymin>
			<xmax>1933</xmax>
			<ymax>2992</ymax>
		</bndbox>
	</object>
</annotation>
